pyvalhalla_weekly.libs/libaec-91f0ca0f.so.0.0.8
pyvalhalla_weekly.libs/libarmadillo-b35ffa1e.so.12.6.6
pyvalhalla_weekly.libs/libarpack-042921fd.so.2.1.0
pyvalhalla_weekly.libs/libblas-fe34f726.so.3.8.0
pyvalhalla_weekly.libs/libbrotlicommon-6ce2a53c.so.1.0.6
pyvalhalla_weekly.libs/libbrotlidec-811d1be3.so.1.0.6
pyvalhalla_weekly.libs/libbsd-526a917f.so.0.12.2
pyvalhalla_weekly.libs/libbz2-a1e77c99.so.1.0.6
pyvalhalla_weekly.libs/libcfitsio-b4c37dff.so.7.3.47
pyvalhalla_weekly.libs/libcom_err-448cbf49.so.2.1
pyvalhalla_weekly.libs/libcrypt-52aca757.so.1.1.0
pyvalhalla_weekly.libs/libcrypto-bdaed0ea.so.1.1.1k
pyvalhalla_weekly.libs/libcurl-c96f124b.so.4.5.0
pyvalhalla_weekly.libs/libczmq-d9886762.so.4.2.1
pyvalhalla_weekly.libs/libdap-7e467616.so.25.0.1
pyvalhalla_weekly.libs/libdapclient-5ca79ace.so.6.1.7
pyvalhalla_weekly.libs/libdapserver-e7ab5c47.so.7.6.7
pyvalhalla_weekly.libs/libdf-2848fafa.so.0.0.0
pyvalhalla_weekly.libs/libexpat-d2b8ed35.so.1.6.7
pyvalhalla_weekly.libs/libfontconfig-dcb2ce6c.so.1.12.0
pyvalhalla_weekly.libs/libfreetype-2f3b32b6.so.6.16.1
pyvalhalla_weekly.libs/libfreexl-25540f57.so.1.2.0
pyvalhalla_weekly.libs/libgdal-bed6323b.so.26.0.4
pyvalhalla_weekly.libs/libgeos-40815548.so.3.13.1
pyvalhalla_weekly.libs/libgeos_c-386b0945.so.1.19.2
pyvalhalla_weekly.libs/libgeotiff-cfdb9fd6.so.5.0.0
pyvalhalla_weekly.libs/libgfortran-8f1e9814.so.5.0.0
pyvalhalla_weekly.libs/libgif-5ed6ffef.so.7.0.0
pyvalhalla_weekly.libs/libgomp-870cb1d0.so.1.0.0
pyvalhalla_weekly.libs/libgssapi_krb5-323bbd21.so.2.2
pyvalhalla_weekly.libs/libgta-6ed1f83a.so.1.0.0
pyvalhalla_weekly.libs/libhdf5-b5e70f84.so.103.1.0
pyvalhalla_weekly.libs/libhdf5_hl-0b60eabd.so.100.1.2
pyvalhalla_weekly.libs/libidn2-2f4a5893.so.0.3.6
pyvalhalla_weekly.libs/libjasper-61dc4fbf.so.4.0.0
pyvalhalla_weekly.libs/libjbig-2504a0c3.so.2.1
pyvalhalla_weekly.libs/libjpeg-e87d2658.so.62.2.0
pyvalhalla_weekly.libs/libjson-c-53e1d64f.so.4.0.0
pyvalhalla_weekly-3.5.1.post1.dev244.dist-info/METADATA
pyvalhalla_weekly-3.5.1.post1.dev244.dist-info/WHEEL
pyvalhalla_weekly-3.5.1.post1.dev244.dist-info/entry_points.txt
pyvalhalla_weekly-3.5.1.post1.dev244.dist-info/top_level.txt
pyvalhalla_weekly-3.5.1.post1.dev244.dist-info/RECORD
pyvalhalla_weekly-3.5.1.post1.dev244.dist-info/licenses/AUTHORS
pyvalhalla_weekly-3.5.1.post1.dev244.dist-info/licenses/COPYING
pyvalhalla_weekly-3.5.1.post1.dev244.dist-info/licenses/LICENSE.md
