Metadata-Version: 2.4
Name: pyvalhalla-weekly
Version: 3.5.1.post1.dev244
Summary: High-level bindings to the Valhalla C++ library
Home-page: https://github.com/valhalla/valhalla
Author: Nils Nolde
Author-email: nilsnolde+pyvalhalla@proton.me
Classifier: License :: OSI Approved :: MIT License
Classifier: Programming Language :: Python :: 3
Classifier: Programming Language :: Python :: Implementation :: CPython
Requires-Python: >=3.9.0
License-File: LICENSE.md
License-File: COPYING
License-File: AUTHORS
Dynamic: author
Dynamic: author-email
Dynamic: classifier
Dynamic: description
Dynamic: description-content-type
Dynamic: home-page
Dynamic: license-file
Dynamic: requires-python
Dynamic: summary
